blenderproc/__init__.py
blenderproc/__main__.py
blenderproc/command_line.py
blenderproc/debug_startup.py
blenderproc/version.py
blenderproc/api/__init__.py
blenderproc/api/camera/__init__.py
blenderproc/api/constructor/__init__.py
blenderproc/api/filter/__init__.py
blenderproc/api/lighting/__init__.py
blenderproc/api/loader/__init__.py
blenderproc/api/material/__init__.py
blenderproc/api/math/__init__.py
blenderproc/api/object/__init__.py
blenderproc/api/postprocessing/__init__.py
blenderproc/api/renderer/__init__.py
blenderproc/api/sampler/__init__.py
blenderproc/api/types/__init__.py
blenderproc/api/utility/__init__.py
blenderproc/api/world/__init__.py
blenderproc/api/writer/__init__.py
blenderproc/external/__init__.py
blenderproc/external/vhacd/__init__.py
blenderproc/external/vhacd/build_linux.sh
blenderproc/external/vhacd/decompose.py
blenderproc/python/__init__.py
blenderproc/python/camera/CameraProjection copy.py
blenderproc/python/camera/CameraProjection.py
blenderproc/python/camera/CameraUtility.py
blenderproc/python/camera/CameraValidation.py
blenderproc/python/camera/LensDistortionUtility.py
blenderproc/python/camera/__init__.py
blenderproc/python/constructor/RandomRoomConstructor.py
blenderproc/python/constructor/__init__.py
blenderproc/python/filter/Filter.py
blenderproc/python/filter/__init__.py
blenderproc/python/lighting/IntersectingSpotLight.py
blenderproc/python/lighting/SuncgLighting.py
blenderproc/python/lighting/SurfaceLighting.py
blenderproc/python/lighting/__init__.py
blenderproc/python/loader/AMASSLoader.py
blenderproc/python/loader/BlendLoader.py
blenderproc/python/loader/BopLoader.py
blenderproc/python/loader/CCMaterialLoader.py
blenderproc/python/loader/Front3DLoader.py
blenderproc/python/loader/HavenEnvironmentLoader.py
blenderproc/python/loader/HavenMaterialLoader.py
blenderproc/python/loader/IKEALoader.py
blenderproc/python/loader/Matterport3DLoader.py
blenderproc/python/loader/ObjectLoader.py
blenderproc/python/loader/Pix3DLoader.py
blenderproc-2.8.0.dist-info/LICENSE
blenderproc-2.8.0.dist-info/METADATA
blenderproc-2.8.0.dist-info/WHEEL
blenderproc-2.8.0.dist-info/entry_points.txt
blenderproc-2.8.0.dist-info/top_level.txt
blenderproc-2.8.0.dist-info/RECORD
