Metadata-Version: 2.1
Name: blenderproc
Version: 2.8.0
Home-page: https://github.com/DLR-RM/BlenderProc
Author: Maximilian Denninger, Dominik Winkelbauer, Martin Sundermeyer
Maintainer: Dominik Winkelbauer
License-File: LICENSE
